itellicoai/__init__.py
itellicoai/_base_client.py
itellicoai/_client.py
itellicoai/_compat.py
itellicoai/_constants.py
itellicoai/_exceptions.py
itellicoai/_files.py
itellicoai/_models.py
itellicoai/_qs.py
itellicoai/_resource.py
itellicoai/_response.py
itellicoai/_streaming.py
itellicoai/_types.py
itellicoai/_version.py
itellicoai/py.typed
itellicoai/_utils/__init__.py
itellicoai/_utils/_compat.py
itellicoai/_utils/_datetime_parse.py
itellicoai/_utils/_logs.py
itellicoai/_utils/_proxy.py
itellicoai/_utils/_reflection.py
itellicoai/_utils/_resources_proxy.py
itellicoai/_utils/_streams.py
itellicoai/_utils/_sync.py
itellicoai/_utils/_transform.py
itellicoai/_utils/_typing.py
itellicoai/_utils/_utils.py
itellicoai/lib/.keep
itellicoai/resources/__init__.py
itellicoai/resources/agents.py
itellicoai/resources/accounts/__init__.py
itellicoai/resources/accounts/accounts.py
itellicoai/resources/accounts/analytics.py
itellicoai/resources/accounts/phone_numbers.py
itellicoai/resources/accounts/providers.py
itellicoai/resources/accounts/sip_trunks.py
itellicoai/resources/accounts/subaccounts.py
itellicoai/types/__init__.py
itellicoai/types/account.py
itellicoai/types/account_list_conversations_params.py
itellicoai/types/account_list_conversations_response.py
itellicoai/types/agent_create_params.py
itellicoai/types/agent_list_params.py
itellicoai/types/agent_list_response.py
itellicoai/types/agent_response.py
itellicoai/types/agent_update_params.py
itellicoai/types/ambient_sound.py
itellicoai/types/ambient_sound_param.py
itellicoai/types/azure_transcriber_param.py
itellicoai/types/capture_settings.py
itellicoai/types/capture_settings_param.py
itellicoai/types/conversation_direction.py
itellicoai/types/conversation_status.py
itellicoai/types/conversation_type.py
itellicoai/types/deepgram_transcriber_param.py
itellicoai/types/denoising.py
itellicoai/types/denoising_param.py
itellicoai/types/inactivity_settings.py
itellicoai/types/inactivity_settings_param.py
itellicoai-1.0.0.dist-info/METADATA
itellicoai-1.0.0.dist-info/WHEEL
itellicoai-1.0.0.dist-info/licenses/LICENSE
itellicoai-1.0.0.dist-info/RECORD
